serena/__init__.py
serena/ensemble_variation.py
serena/local_minima_variation.py
serena/switchyness_score.py
serena/analysis/__init__.py
serena/analysis/ensemble_analysis.py
serena/analysis/investigator.py
serena/analysis/judge_pool.py
serena/analysis/scoring.py
serena/bin/__init__.py
serena/bin/backup_investigator_v1.py
serena/bin/backup_serena_v2.py
serena/examples/__init__.py
serena/examples/switch_acceptance.py
serena/interfaces/Sara2_API_Python3.py
serena/interfaces/__init__.py
serena/interfaces/eterna_interface.py
serena/interfaces/nupack4_0_28_wsl2_interface.py
serena/interfaces/vienna2_fmn_hack_interface.py
serena/scripts/__init__.py
serena/scripts/analyze_pnas_2112979119_sd01.py
serena/tests/__init__.py
serena/tests/conftest.py
serena/tests/entry_point/__init__.py
serena/tests/entry_point/test_entry_ensemble_variation.py
serena/tests/entry_point/test_entry_groups.py
serena/tests/entry_point/test_entry_structures.py
serena/tests/entry_point/test_switchyness_score.py
serena/tests/utilities/__init__.py
serena/tests/utilities/test_comparison_structures.py
serena/tests/utilities/test_ensemble_groups.py
serena/tests/utilities/test_ensemble_variation.py
serena/tests/utilities/test_local_minima_variation.py
serena/tests/utilities/test_multiple_ensemble_groups.py
serena/tests/utilities/test_nupack4_interface.py
serena/tests/utilities/test_sara_secondary_structure.py
serena/tests/utilities/test_sara_secondary_structure_lists.py
serena/tests/utilities/test_weighted_structures.py
serena/utilities/__init__.py
serena/utilities/comparison_structures.py
serena/utilities/ensemble_groups.py
serena/utilities/ensemble_structures.py
serena/utilities/ensemble_variation.py
serena/utilities/local_minima_variation.py
serena/utilities/logging_serena.py
serena/utilities/plots.py
serena/utilities/report_generation.py
serena/utilities/thread_manager.py
serena/utilities/weighted_structures.py
serena_rna_tool-3.0.0.0.dist-info/LICENSE
serena_rna_tool-3.0.0.0.dist-info/METADATA
serena_rna_tool-3.0.0.0.dist-info/WHEEL
serena_rna_tool-3.0.0.0.dist-info/entry_points.txt
serena_rna_tool-3.0.0.0.dist-info/top_level.txt
serena_rna_tool-3.0.0.0.dist-info/RECORD
