Metadata-Version: 2.1
Name: serena_rna_tool
Version: 3.0.0.0
Summary: Serena RNA toolset for ensemble analysis with data-nut-squirrel data archive implementation
Author-email: Jennifer Pearl <jenpearl5@gmail.com>
License:                     GNU GENERAL PUBLIC LICENSE
Project-URL: Homepage, https://lunarfawn.github.io/serena_documentation/
Project-URL: Repository, https://github.com/LunarFawn/Serena-Local-Minima-Variation-Tool.git
Classifier: Programming Language :: Python
Classifier: Programming Language :: Python :: 3
Requires-Python: <3.10
License-File: LICENSE
